{
  "color": {
    "black-alpha": {
      "00": "#00000000",
      "04": "#0000000a",
      "07": "#00000012",
      "11": "#0000001c",
      "20": "#00000033",
      "30": "#0000004d",
      "40": "#00000066",
      "50": "#00000080",
      "60": "#00000099",
      "70": "#000000b3",
      "80": "#000000cc",
      "90": "#000000e6",
      "95": "#000000f2",
      "100": "#000000"
    },
    "blue": {
      "05": "#edf8ff",
      "10": "#dbf0ff",
      "20": "#bfe3ff",
      "30": "#96d0ff",
      "40": "#64b4fa",
      "50": "#3492eb",
      "60": "#1170cf",
      "70": "#0353a8",
      "80": "#063a75",
      "90": "#0a274a",
      "95": "#091a30",
      "100": "#07101c"
    },
    "gray": {
      "05": "#f7f7f7",
      "10": "#ededed",
      "20": "#dedede",
      "30": "#c9c9c9",
      "40": "#adadad",
      "50": "#8f8f8f",
      "60": "#707070",
      "70": "#545454",
      "80": "#3b3b3b",
      "90": "#262626",
      "95": "#1a1a1a",
      "100": "#0f0f0f"
    },
    "green": {
      "05": "#edf7f5",
      "10": "#cef5eb",
      "20": "#9fedd8",
      "30": "#68debd",
      "40": "#3cc29a",
      "50": "#27a17a",
      "60": "#1d805f",
      "70": "#185e46",
      "80": "#134231",
      "90": "#0e2b20",
      "95": "#0a1c15",
      "100": "#07120d",
      "105": "#4e6961"
    },
    "red": {
      "05": "#fff5f6",
      "10": "#ffe8ea",
      "20": "#ffd4da",
      "30": "#ffb8c1",
      "40": "#fc8b98",
      "50": "#f55868",
      "60": "#db1f2e",
      "70": "#ab0a15",
      "80": "#780d13",
      "90": "#4f0e10",
      "95": "#330d0e",
      "100": "#1f0a0a"
    },
    "transparent": "rgba(255, 255, 255, 0)",
    "white-alpha": {
      "00": "#ffffff00",
      "05": "#ffffff0d",
      "07": "#ffffff12",
      "11": "#ffffff1c",
      "20": "#ffffff33",
      "30": "#ffffff4d",
      "40": "#ffffff66",
      "50": "#ffffff80",
      "60": "#ffffff99",
      "70": "#ffffffb3",
      "80": "#ffffffcc",
      "90": "#ffffffe6",
      "95": "#fffffff2",
      "100": "#ffffff"
    },
    "yellow": {
      "05": "#fff6e3",
      "10": "#ffebc2",
      "20": "#ffda94",
      "30": "#ffbe4f",
      "40": "#f2990a",
      "50": "#cf7900",
      "60": "#a65e00",
      "70": "#7d4705",
      "80": "#57330a",
      "90": "#36220c",
      "95": "#24180b",
      "100": "#140e08"
    }
  }
}
